azure_table_utils/__init__.py
azure_table_utils/main.py
azure_table_utils/utils.py
azure_table_utils-0.0.6.dist-info/METADATA
azure_table_utils-0.0.6.dist-info/WHEEL
azure_table_utils-0.0.6.dist-info/licenses/LICENSE
azure_table_utils-0.0.6.dist-info/RECORD
