Metadata-Version: 2.4
Name: azure_table_utils
Version: 0.0.6
Summary: A package to handle Azure Storage Table
Project-URL: Homepage, https://github.com/pypa/sampleproject
Project-URL: Issues, https://github.com/pypa/sampleproject/issues
Author-email: Rafael Oliveira <r.negreiros@outlook.com.br>
License-Expression: MIT
License-File: LICENSE
Classifier: Operating System :: OS Independent
Classifier: Programming Language :: Python :: 3
Requires-Python: >=3.11.8
Requires-Dist: azure-core>=1.34.0
Requires-Dist: azure-data-tables>=12.7.0
Requires-Dist: python-dotenv
